defipy/__init__.py
defipy/agents/ImpermanentLossAgent.py
defipy/agents/PriceThresholdSwapAgent.py
defipy/agents/TVLBasedLiquidityExitAgent.py
defipy/agents/VolumeSpikeNotifierAgent.py
defipy/agents/__init__.py
defipy/agents/config/ImpermanentLossConfig.py
defipy/agents/config/PriceThresholdConfig.py
defipy/agents/config/TVLExitConfig.py
defipy/agents/config/VolumeSpikeConfig.py
defipy/agents/config/__init__.py
defipy/agents/data/UniswapPoolData.py
defipy/agents/data/__init__.py
defipy/analytics/risk/__init__.py
defipy/analytics/simulate/__init__.py
defipy/erc/__init__.py
defipy/math/basic/__init__.py
defipy/math/interest/__init__.py
defipy/math/interest/ips/__init__.py
defipy/math/interest/ips/aggregate/__init__.py
defipy/math/model/__init__.py
defipy/math/risk/__init__.py
defipy/process/__init__.py
defipy/process/burn/__init__.py
defipy/process/deposit/__init__.py
defipy/process/join/Join.py
defipy/process/join/__init__.py
defipy/process/liquidity/AddLiquidity.py
defipy/process/liquidity/RemoveLiquidity.py
defipy/process/liquidity/__init__.py
defipy/process/mint/__init__.py
defipy/process/swap/Swap.py
defipy/process/swap/__init__.py
defipy/utils/client/__init__.py
defipy/utils/client/contract/ExecuteScript.py
defipy/utils/client/contract/__init__.py
defipy/utils/data/__init__.py
defipy/utils/interfaces/__init__.py
defipy/utils/tools/UniswapScriptHelper.py
defipy/utils/tools/__init__.py
defipy/utils/tools/v3/__init__.py
defipy-1.0.9.dist-info/licenses/LICENSE
defipy-1.0.9.dist-info/licenses/NOTICE
defipy-1.0.9.dist-info/METADATA
defipy-1.0.9.dist-info/WHEEL
defipy-1.0.9.dist-info/top_level.txt
defipy-1.0.9.dist-info/RECORD
