Metadata-Version: 2.4
Name: DeFiPy
Version: 1.0.9
Summary: Python SDK for DeFi Analytics, Simulation, and Agents
Home-page: http://github.com/defipy-devs/defipy
Author: icmoore
Author-email: defipy.devs@gmail.com
License: Apache-2.0
Classifier: License :: OSI Approved :: Apache Software License
Classifier: Programming Language :: Python :: 3
Classifier: Operating System :: OS Independent
Classifier: Intended Audience :: Developers
Classifier: Topic :: Software Development :: Libraries :: Python Modules
Classifier: Topic :: Scientific/Engineering :: Information Analysis
Classifier: Topic :: Internet :: WWW/HTTP :: Dynamic Content
License-File: LICENSE
License-File: NOTICE
Requires-Dist: scipy>=1.7.3
Requires-Dist: pydantic>=2.11.0
Requires-Dist: bokeh==3.3.4
Requires-Dist: uniswappy>=1.7.4
Requires-Dist: stableswappy>=1.0.3
Requires-Dist: balancerpy>=1.0.4
Dynamic: author
Dynamic: author-email
Dynamic: classifier
Dynamic: description
Dynamic: description-content-type
Dynamic: home-page
Dynamic: license
Dynamic: license-file
Dynamic: requires-dist
Dynamic: summary
